{
  "name": "Fannie Sharp",
  "age": 38,
  "address": {
    "street": "Moah Street",
    "city": "Luhfiena",
    "state": "WV",
    "zip": "52192"
  },
  "contact": {
    "phone": "(848) 285-4448",
    "servicePhone": "800228259"
  },
  "birthday": "1986-01-22T03:20:07.815Z",
  "ip": "170.6.44.80",
  "foo": "bar",
  "profile": {
    "about": "Desepefo muh pinepe tepop bihajkeb ogabifofi sadotlul olruziha hiwnikic lonpazpi hi nu tic ovsi ipikipof wijvo cimsigih awede. Hafopi zofi debzon ne vafa aveahnik watafu gaahum wito ed ro mob nojoluj penejuj zevuj kumzahuw ufica. Fotluraj iligikdap un fe bo nuosico ehioje vuvahco tajmili bo cu et ga po sat evi. Alojujoco zej hujwe hebrosbog op gep gehmike wervomru jit hickuf nopakdo fid. Feon nomep cofpa neljij powzofiwa legi pupuv lupbukla vas icakehet oj hep sekok ih haguk dawcek fozduju fe.",
    "bio": "On gi da guszos kavudun tusfajco hu voj wuvfen vozelpi sij vowesekak re ru pihisu unmeb. Hokevipod cam lierhi tiet fiz uvnen hutem ulseali roshu pewgu ivimuos igu vife. Ejoafa joru zejba tin avtaaki lif wog fa ih tawtiow buvotad si dacewir toloip igeav go batatale ad. Gocto bojlen opharam vezekev mudepauj efibvu utu kat kusat getzuk ig tedi sokga cofnidmub. Aba suztuaf vir vonfoh zo podlof gan jufigote ubacedgaf moabisaj wohip cihubu geaduwe ezuca siboc cevohe limula muf. Fomfek ub bas ritinave zid akze pe wonge co geebdi sejo pazru."
  },
  "apiKey": "047abaf24c95b108585de5a7d1882fb46963ab09ecc3f47be5e313e68a3d7530",
  "currency": {
    "code": "XDR",
    "name": "International Monetary Fund (IMF) Special Drawing Rights"
  }
}