{
  "name": "Randy Weaver",
  "age": 25,
  "address": {
    "street": "Wivdo Square",
    "city": "Feehiwi",
    "state": "CA",
    "zip": "56829"
  },
  "contact": {
    "phone": "(600) 529-6088",
    "servicePhone": "800574224"
  },
  "birthday": "1997-08-02T09:27:18.649Z",
  "ip": "251.227.240.165",
  "foo": "bar",
  "profile": {
    "about": "Ro muab ludohje gi ot no ira lif pupvepcuc wibat potna lowifi sijfana heh aj. Ru luhos dawraej osoravet hep uhnub mained tim kugvahrul jit edjor wud rifod. Hukoc rakbiv uloif asdagvod libmu pek meba uz admuoj gaambem kehanow cud vuuni. Gulzuzni poguhube ikkeuvo efib emhok digiugi fosu ziasfiz sepjipgav kuju daf re zogbuw ruahezi wu go.",
    "bio": "Kozigile abawa tiutce ve secij rennim pazi ludi catohcon himioh hel rusjode lewdu rujobu ciso. Sib ci genomu zolzeto ujegogum feju zec waze cofho egicas diw cimu ozeifu reonu du eg naomomem vuzu. Relwowuf de wawep hibke liljujawi pobwek ratjiz pid nagfohjut ceita uma tokodig ufrico pietzo ovkewju. Fo on tacioda zap pejnibsed nit ehoez bobfop gaw siife riojajo dagu puwerkof mo wuoghu kazi. Gitooz gid ke powu nimev kurigka vi duehuhit talwon did meivkez jek warkajmek tokkaj. Ci peib aznidred buwki ape nuko hot ponekohab rul gaujra puurigun janric."
  },
  "apiKey": "9db5fa2e078b116768eb1c5be74e48d027013ced10d404559ca1c04207002a93",
  "currency": {
    "code": "CDF",
    "name": "Congo/Kinshasa Franc"
  }
}