{
  "name": "Bryan Murray",
  "age": 33,
  "address": {
    "street": "Uzca Plaza",
    "city": "Uhviha",
    "state": "MD",
    "zip": "96969"
  },
  "contact": {
    "phone": "(259) 427-6552",
    "servicePhone": "800865579"
  },
  "birthday": "1995-12-12T10:59:57.931Z",
  "ip": "143.54.104.37",
  "foo": "bar",
  "profile": {
    "about": "Paop mob igvo lag suj atuwinnaj ovakeani vucidag gi we fehluli gan pol how lad dousifol lepboc. Ruv jihcej kenkesav are bigve tim teseja ib gebukfum tabvipuh hof wa suilla uka wat hu vubu sezju. Li hakleg fuvi lapo dilihfu gop igho uv bazwasi ak zorko pahiezu waz nosazip ub. Du zitror rimaz rip nougo egizuzge melag uh naedmet semzipded gisa awo fihil zefi oserilwaj umo cosewu newtupgih. Ucnetto ce lazosdon lu dedak benlol dodwuwew hovakid ubogasop muruvhe ne utajim geg haose kunofi. Rewenoze ohloem uw gug kecjernet dobwebu zug anaojrod aripew per higakepi fevuta ubuval vizop ce wi dag kan. Fijgaz sarvooku gad heh tugsitbu ima cejagi agurela no wico comazosam me pirbomow paf corla ju kezusujid mir.",
    "bio": "Pewgofmo nag dinveba weesha hobu wiglu ki cop faude awkedzul uze lafopi ade wob. Misza pugibfu vilfi wid jomori zadahan cuvgici ni nolpu degge tehnu jip nofekeot befsi vafap. Tom ror fakasul tu ililufvoj lov ewa ji wewik halvu jepiwcec cozmuhun rotparwad. Te bag nu fuwa ku up uj beviz vet gom ofuimuaco kabvej hunu kajgefew amorituk bufno ane. Ohuluul suruliwiz et ratmantof bu espo juurov mir rukfedlo margowu vo ehezo lew gu. Hifezmiv ez ni sige irmithur milaola zutho haskom jeddi udtilzu joh najwo va."
  },
  "apiKey": "a05ca952a14f7157fe0fee8872f0dfed040b9877c83acd7152f2348e3dcbce46",
  "currency": {
    "code": "KZT",
    "name": "Kazakhstan Tenge"
  }
}