{
  "name": "Minerva Sandoval",
  "age": 38,
  "address": {
    "street": "Sahmo Lane",
    "city": "Zizsumrip",
    "state": "WI",
    "zip": "47103"
  },
  "contact": {
    "phone": "(573) 539-4732",
    "servicePhone": "800853638"
  },
  "birthday": "1975-07-09T03:30:34.001Z",
  "ip": "162.255.208.249",
  "foo": "bar",
  "profile": {
    "about": "Vibmus fomiize urievu du walcovjuv pupum zijwi fot uwga viisilam vok ulvo hitu uzetob uw vub wivsowol ugegodap. Giteceri pajnap av hismus mosrala saw mi zu ip zezor keras efugetu. Dagwalas citgoep rizgaapu wuhhigfo nezopaso jo fo wezab dumi iwuguwten si iprores. Hu rovsofu wuhuru omi segetpug su gobeha pot wev asupogka tubcamce la re zazmu mol ninuja nofsuh. Poabufe daagcir zi bafu gafcoc cila pi digot fe pe akielhiv la uz us nucuzlu.",
    "bio": "Obman fi piknom ni puhuvi iwukotan bep kuna renoaha bajlome tu abjeozu zi sit degsaatu udsa epdurot. Pi suru lufauw vufjon huokonev jolo kijzo kito ursisu nadloiv deji lisut pi pihguj os epjupcej. Ero lutughac toc kefgirva jotuz osramki wefus minabade ojowejpot otirizvan ba jud ze. Ame imure ko zewcat am renfobub bemhi jifor kiz zomuvgab ponboela zupfec. Tehfi ivupu putomhu iwi nopgo ga otetekgo evbisag zev samvugdic jenop cobpo. Bedrut morwacab jokbihte kobad ficakol peondir ajilucdah zuzlapfef fu lu zigin jenunatuk."
  },
  "apiKey": "d64953e8b505d116e6d31af9907e16afe81106121581acd86096a30152d527c8",
  "currency": {
    "code": "CHF",
    "name": "Switzerland Franc"
  }
}